pybioimage/__init__.py
pybioimage/utils.py
pybioimage/aggregation/__init__.py
pybioimage/aggregation/analyzer.py
pybioimage/aggregation/image.py
pybioimage/enrichment/__init__.py
pybioimage/enrichment/analyzer.py
pybioimage/frap/__init__.py
pybioimage/frap/analyzer.py
pybioimage-0.1.0.dist-info/licenses/LICENSE
pybioimage-0.1.0.dist-info/WHEEL
pybioimage-0.1.0.dist-info/METADATA
pybioimage-0.1.0.dist-info/RECORD
