Metadata-Version: 2.4
Name: pybioimage
Version: 0.1.0
Summary: A small package for custom image analysis tasks.
Author-email: Raphael Schleutker <raphaelschleutker@gmx.de>
Requires-Python: >=3.12
License-File: LICENSE
Requires-Dist: scikit-image>=0.22.0
Requires-Dist: opencv-python>=4.6.0
Requires-Dist: numpy>=1.26.4
Requires-Dist: pandas>=2.2.1
Requires-Dist: pykuwahara>=0.3.2
Requires-Dist: black ; extra == "dev"
Requires-Dist: pytest>=8.3.4 ; extra == "test"
Provides-Extra: dev
Provides-Extra: test
